LinAlgebraPy/__init__.py
LinAlgebraPy/matrices/__init__.py
LinAlgebraPy/matrices/matrix.py
LinAlgebraPy/matrices/matrixfunc.py
LinAlgebraPy/sets/__init__.py
LinAlgebraPy/sets/generalSet.py
LinAlgebraPy/sets/setofmatrices.py
LinAlgebraPy/sets/setofvectors.py
LinAlgebraPy/vectors/__init__.py
LinAlgebraPy/vectors/vector.py
LinAlgebraPy/vectors/vectorfunc.py
test/__init__.py
test/test_m.py
LinAlgebraPy-0.1.4.dist-info/LICENSE
LinAlgebraPy-0.1.4.dist-info/METADATA
LinAlgebraPy-0.1.4.dist-info/WHEEL
LinAlgebraPy-0.1.4.dist-info/top_level.txt
LinAlgebraPy-0.1.4.dist-info/RECORD
