Metadata-Version: 2.1
Name: LinAlgebraPy
Version: 0.1.4
Summary: Linear Algebra Package
Home-page: UNKNOWN
Author: Rami El Dahouk
Author-email: ramipypi@outlook.com
License: MIT
Platform: UNKNOWN
Requires-Python: >=3.5
License-File: LICENSE
